{"description":"General purpose button, built on top of Material-UI button","displayName":"Button","methods":[{"name":"getProps","docblock":null,"modifiers":[],"params":[],"returns":null}],"props":{"classes":{"type":{"name":"shape","value":{"root":{"name":"string","required":false},"iconButton":{"name":"string","required":false},"leftIcon":{"name":"string","required":false},"rightIcon":{"name":"string","required":false},"raised":{"name":"string","required":false},"noLabel":{"name":"string","required":false}}},"required":false,"description":"Internal classNames used by Button component"},"className":{"type":{"name":"string"},"required":false,"description":"Root classname to override"},"to":{"type":{"name":"string"},"required":false,"description":"React router path if no onClick callback specified"},"onClick":{"type":{"name":"func"},"required":false,"description":"Function call when button clicked"},"leftIcon":{"type":{"name":"node"},"required":false,"description":"React Node on the left on the button content, use for icon"},"rightIcon":{"type":{"name":"node"},"required":false,"description":"React Node on the right on the button content, use for icon"},"label":{"type":{"name":"string"},"required":false,"description":"Button label"},"icon":{"type":{"name":"node"},"required":false,"description":"Use icon instead of string for button content"},"raised":{"type":{"name":"bool"},"required":false,"description":"Toggle raised type button","defaultValue":{"value":"true","computed":false}},"disabled":{"type":{"name":"bool"},"required":false,"description":""},"leftGutter":{"type":{"name":"bool"},"required":false,"description":"Add margin left to the button"},"rightGutter":{"type":{"name":"bool"},"required":false,"description":"Add margin right to the button"},"small":{"type":{"name":"bool"},"required":false,"description":"Render smaller button"},"color":{"type":{"name":"string"},"required":false,"description":"Override button color","defaultValue":{"value":"'default'","computed":false}}}}